motcha/__init__.py
motcha-0.0.0.dist-info/METADATA
motcha-0.0.0.dist-info/WHEEL
motcha-0.0.0.dist-info/RECORD
